MANIFEST.in
README.rst
cherrys.py
setup.py
cherrys.egg-info/PKG-INFO
cherrys.egg-info/SOURCES.txt
cherrys.egg-info/dependency_links.txt
cherrys.egg-info/requires.txt
cherrys.egg-info/top_level.txt