Metadata-Version: 1.0
Name: cherrys
Version: 0.4
Summary: Redis backend for CherryPy sessions
Home-page: http://github.com/3kwa/cherrys
Author: Eugene Van den Bulke
Author-email: eugene.vandenbulke@gmail.com
License: MIT
Platform: UNKNOWN
Classifier: Development Status :: 5 - Production/Stable
Classifier: Environment :: Web Environment
Classifier: Framework :: CherryPy
Classifier: Intended Audience :: Developers
Classifier: License :: Freely Distributable
Classifier: Operating System :: OS Independent
Classifier: Programming Language :: Python
Classifier: Topic :: Database
Classifier: Topic :: Internet :: WWW/HTTP :: Session
